anime_from_terminal/__init__.py
anime_from_terminal/anime_dl.py
anime_from_terminal/fetch_info.py
anime_from_terminal/main.py
anime_from_terminal/mcp_server.py
anime_from_terminal-1.2.0.dist-info/licenses/LICENSE
anime_from_terminal-1.2.0.dist-info/METADATA
anime_from_terminal-1.2.0.dist-info/WHEEL
anime_from_terminal-1.2.0.dist-info/entry_points.txt
anime_from_terminal-1.2.0.dist-info/top_level.txt
anime_from_terminal-1.2.0.dist-info/RECORD
