Metadata-Version: 2.4
Name: anime-from-terminal
Version: 1.2.0
Summary: Watch anime from your terminal
Requires-Python: >=3.14
License-File: LICENSE
Requires-Dist: colorama>=0.4.6
Requires-Dist: iterfzf>=1.8.0.62.0
Requires-Dist: mcp[cli]>=1.26.0
Requires-Dist: requests>=2.32.5
Dynamic: license-file
